<?xml version="1.0" encoding="utf-8" standalone="yes"?>
<Gesture Name = "a inval circle 1">
	<Stroke>
		<Point X = "270" Y = "-114.875" T = "0" Pressure = "0" />
		<Point X = "270" Y = "-118.625" T = "0" Pressure = "0" />
		<Point X = "270" Y = "-118.625" T = "0" Pressure = "0" />
		<Point X = "270" Y = "-121.125" T = "0" Pressure = "0" />
		<Point X = "270" Y = "-127.375" T = "0" Pressure = "0" />
		<Point X = "270" Y = "-133.625" T = "0" Pressure = "0" />
		<Point X = "270" Y = "-133.625" T = "0" Pressure = "0" />
		<Point X = "270" Y = "-138.625" T = "0" Pressure = "0" />
		<Point X = "270" Y = "-144.875" T = "0" Pressure = "0" />
		<Point X = "270" Y = "-144.875" T = "0" Pressure = "0" />
		<Point X = "270" Y = "-152.375" T = "0" Pressure = "0" />
		<Point X = "270" Y = "-159.875" T = "0" Pressure = "0" />
		<Point X = "270" Y = "-159.875" T = "0" Pressure = "0" />
		<Point X = "267.5" Y = "-169.875" T = "0" Pressure = "0" />
		<Point X = "263.75" Y = "-178.625" T = "0" Pressure = "0" />
		<Point X = "263.75" Y = "-178.625" T = "0" Pressure = "0" />
		<Point X = "262.5" Y = "-188.625" T = "0" Pressure = "0" />
		<Point X = "258.75" Y = "-199.875" T = "0" Pressure = "0" />
		<Point X = "258.75" Y = "-199.875" T = "0" Pressure = "0" />
		<Point X = "253.75" Y = "-214.875" T = "0" Pressure = "0" />
		<Point X = "251.25" Y = "-227.375" T = "0" Pressure = "0" />
		<Point X = "251.25" Y = "-227.375" T = "0" Pressure = "0" />
		<Point X = "246.25" Y = "-242.375" T = "0" Pressure = "0" />
		<Point X = "242.5" Y = "-258.625" T = "0" Pressure = "0" />
		<Point X = "242.5" Y = "-258.625" T = "0" Pressure = "0" />
		<Point X = "237.5" Y = "-274.875" T = "0" Pressure = "0" />
		<Point X = "235" Y = "-294.875" T = "0" Pressure = "0" />
		<Point X = "235" Y = "-294.875" T = "0" Pressure = "0" />
		<Point X = "232.5" Y = "-314.875" T = "0" Pressure = "0" />
		<Point X = "232.5" Y = "-333.625" T = "0" Pressure = "0" />
		<Point X = "232.5" Y = "-333.625" T = "0" Pressure = "0" />
		<Point X = "232.5" Y = "-352.375" T = "0" Pressure = "0" />
		<Point X = "232.5" Y = "-352.375" T = "0" Pressure = "0" />
		<Point X = "233.75" Y = "-371.125" T = "0" Pressure = "0" />
		<Point X = "242.5" Y = "-384.875" T = "0" Pressure = "0" />
		<Point X = "253.75" Y = "-399.875" T = "0" Pressure = "0" />
		<Point X = "253.75" Y = "-399.875" T = "0" Pressure = "0" />
		<Point X = "262.5" Y = "-409.875" T = "0" Pressure = "0" />
		<Point X = "273.75" Y = "-418.625" T = "0" Pressure = "0" />
		<Point X = "273.75" Y = "-418.625" T = "0" Pressure = "0" />
		<Point X = "287.5" Y = "-424.875" T = "0" Pressure = "0" />
		<Point X = "295" Y = "-427.375" T = "0" Pressure = "0" />
		<Point X = "295" Y = "-427.375" T = "0" Pressure = "0" />
		<Point X = "303.75" Y = "-429.875" T = "0" Pressure = "0" />
		<Point X = "312.5" Y = "-433.625" T = "0" Pressure = "0" />
		<Point X = "322.5" Y = "-436.125" T = "0" Pressure = "0" />
		<Point X = "322.5" Y = "-436.125" T = "0" Pressure = "0" />
		<Point X = "332.5" Y = "-437.375" T = "0" Pressure = "0" />
		<Point X = "340" Y = "-437.375" T = "0" Pressure = "0" />
		<Point X = "340" Y = "-437.375" T = "0" Pressure = "0" />
		<Point X = "350" Y = "-439.875" T = "0" Pressure = "0" />
		<Point X = "356.25" Y = "-439.875" T = "0" Pressure = "0" />
		<Point X = "356.25" Y = "-439.875" T = "0" Pressure = "0" />
		<Point X = "362.5" Y = "-439.875" T = "0" Pressure = "0" />
		<Point X = "375" Y = "-438.625" T = "0" Pressure = "0" />
		<Point X = "375" Y = "-438.625" T = "0" Pressure = "0" />
		<Point X = "388.75" Y = "-431.125" T = "0" Pressure = "0" />
		<Point X = "403.75" Y = "-424.875" T = "0" Pressure = "0" />
		<Point X = "403.75" Y = "-424.875" T = "0" Pressure = "0" />
		<Point X = "423.75" Y = "-413.625" T = "0" Pressure = "0" />
		<Point X = "437.5" Y = "-401.125" T = "0" Pressure = "0" />
		<Point X = "447.5" Y = "-389.875" T = "0" Pressure = "0" />
		<Point X = "457.5" Y = "-377.375" T = "0" Pressure = "0" />
		<Point X = "457.5" Y = "-377.375" T = "0" Pressure = "0" />
		<Point X = "467.5" Y = "-362.375" T = "0" Pressure = "0" />
		<Point X = "473.75" Y = "-347.375" T = "0" Pressure = "0" />
		<Point X = "473.75" Y = "-347.375" T = "0" Pressure = "0" />
		<Point X = "481.25" Y = "-334.875" T = "0" Pressure = "0" />
		<Point X = "481.25" Y = "-334.875" T = "0" Pressure = "0" />
		<Point X = "483.75" Y = "-318.625" T = "0" Pressure = "0" />
		<Point X = "483.75" Y = "-296.125" T = "0" Pressure = "0" />
		<Point X = "483.75" Y = "-284.875" T = "0" Pressure = "0" />
		<Point X = "483.75" Y = "-284.875" T = "0" Pressure = "0" />
		<Point X = "483.75" Y = "-264.875" T = "0" Pressure = "0" />
		<Point X = "483.75" Y = "-264.875" T = "0" Pressure = "0" />
		<Point X = "477.5" Y = "-244.875" T = "0" Pressure = "0" />
		<Point X = "471.25" Y = "-223.625" T = "0" Pressure = "0" />
		<Point X = "461.25" Y = "-206.125" T = "0" Pressure = "0" />
		<Point X = "461.25" Y = "-206.125" T = "0" Pressure = "0" />
		<Point X = "451.25" Y = "-191.125" T = "0" Pressure = "0" />
		<Point X = "438.75" Y = "-174.875" T = "0" Pressure = "0" />
		<Point X = "426.25" Y = "-161.125" T = "0" Pressure = "0" />
		<Point X = "426.25" Y = "-161.125" T = "0" Pressure = "0" />
		<Point X = "415" Y = "-153.625" T = "0" Pressure = "0" />
		<Point X = "415" Y = "-153.625" T = "0" Pressure = "0" />
		<Point X = "403.75" Y = "-144.875" T = "0" Pressure = "0" />
		<Point X = "388.75" Y = "-137.375" T = "0" Pressure = "0" />
		<Point X = "388.75" Y = "-137.375" T = "0" Pressure = "0" />
		<Point X = "376.25" Y = "-131.125" T = "0" Pressure = "0" />
		<Point X = "365" Y = "-126.125" T = "0" Pressure = "0" />
		<Point X = "365" Y = "-126.125" T = "0" Pressure = "0" />
		<Point X = "357.5" Y = "-122.375" T = "0" Pressure = "0" />
		<Point X = "347.5" Y = "-119.875" T = "0" Pressure = "0" />
		<Point X = "347.5" Y = "-119.875" T = "0" Pressure = "0" />
		<Point X = "337.5" Y = "-119.875" T = "0" Pressure = "0" />
		<Point X = "327.5" Y = "-119.875" T = "0" Pressure = "0" />
		<Point X = "313.75" Y = "-119.875" T = "0" Pressure = "0" />
		<Point X = "313.75" Y = "-119.875" T = "0" Pressure = "0" />
		<Point X = "302.5" Y = "-119.875" T = "0" Pressure = "0" />
		<Point X = "291.25" Y = "-119.875" T = "0" Pressure = "0" />
		<Point X = "291.25" Y = "-119.875" T = "0" Pressure = "0" />
	</Stroke>
</Gesture>
