<?xml version="1.0" encoding="utf-8" standalone="yes"?>
<Gesture Name = "a inval 8">
	<Stroke>
		<Point X = "-4.243847" Y = "-0.6199837" T = "0" Pressure = "0" />
		<Point X = "-4.299242" Y = "-0.6757529" T = "0" Pressure = "0" />
		<Point X = "-4.359885" Y = "-0.7408096" T = "0" Pressure = "0" />
		<Point X = "-4.400824" Y = "-0.7872785" T = "0" Pressure = "0" />
		<Point X = "-4.446727" Y = "-0.8422928" T = "0" Pressure = "0" />
		<Point X = "-4.517352" Y = "-0.9208514" T = "0" Pressure = "0" />
		<Point X = "-4.586804" Y = "-0.9925113" T = "0" Pressure = "0" />
		<Point X = "-4.62808" Y = "-1.033864" T = "0" Pressure = "0" />
		<Point X = "-4.660517" Y = "-1.065215" T = "0" Pressure = "0" />
		<Point X = "-4.731726" Y = "-1.137123" T = "0" Pressure = "0" />
		<Point X = "-4.806116" Y = "-1.21324" T = "0" Pressure = "0" />
		<Point X = "-4.885837" Y = "-1.291768" T = "0" Pressure = "0" />
		<Point X = "-4.950886" Y = "-1.354171" T = "0" Pressure = "0" />
		<Point X = "-4.998714" Y = "-1.398646" T = "0" Pressure = "0" />
		<Point X = "-5.084173" Y = "-1.475157" T = "0" Pressure = "0" />
		<Point X = "-5.157456" Y = "-1.539107" T = "0" Pressure = "0" />
		<Point X = "-5.202388" Y = "-1.577831" T = "0" Pressure = "0" />
		<Point X = "-5.272543" Y = "-1.637733" T = "0" Pressure = "0" />
		<Point X = "-5.320574" Y = "-1.678423" T = "0" Pressure = "0" />
		<Point X = "-5.378806" Y = "-1.729676" T = "0" Pressure = "0" />
		<Point X = "-5.419509" Y = "-1.767624" T = "0" Pressure = "0" />
		<Point X = "-5.448862" Y = "-1.797776" T = "0" Pressure = "0" />
		<Point X = "-5.512547" Y = "-1.875866" T = "0" Pressure = "0" />
		<Point X = "-5.564964" Y = "-1.950356" T = "0" Pressure = "0" />
		<Point X = "-5.606072" Y = "-2.013893" T = "0" Pressure = "0" />
		<Point X = "-5.65582" Y = "-2.099539" T = "0" Pressure = "0" />
		<Point X = "-5.683608" Y = "-2.155052" T = "0" Pressure = "0" />
		<Point X = "-5.721656" Y = "-2.264" T = "0" Pressure = "0" />
		<Point X = "-5.737165" Y = "-2.34352" T = "0" Pressure = "0" />
		<Point X = "-5.742847" Y = "-2.413098" T = "0" Pressure = "0" />
		<Point X = "-5.74264" Y = "-2.468138" T = "0" Pressure = "0" />
		<Point X = "-5.733096" Y = "-2.553222" T = "0" Pressure = "0" />
		<Point X = "-5.705996" Y = "-2.670791" T = "0" Pressure = "0" />
		<Point X = "-5.669459" Y = "-2.76855" T = "0" Pressure = "0" />
		<Point X = "-5.625752" Y = "-2.856978" T = "0" Pressure = "0" />
		<Point X = "-5.576289" Y = "-2.93968" T = "0" Pressure = "0" />
		<Point X = "-5.527869" Y = "-3.010989" T = "0" Pressure = "0" />
		<Point X = "-5.46289" Y = "-3.098573" T = "0" Pressure = "0" />
		<Point X = "-5.39794" Y = "-3.179971" T = "0" Pressure = "0" />
		<Point X = "-5.336741" Y = "-3.249457" T = "0" Pressure = "0" />
		<Point X = "-5.247949" Y = "-3.339327" T = "0" Pressure = "0" />
		<Point X = "-5.174244" Y = "-3.408658" T = "0" Pressure = "0" />
		<Point X = "-5.085747" Y = "-3.487924" T = "0" Pressure = "0" />
		<Point X = "-5.046167" Y = "-3.522311" T = "0" Pressure = "0" />
		<Point X = "-4.995772" Y = "-3.56365" T = "0" Pressure = "0" />
		<Point X = "-4.910354" Y = "-3.627181" T = "0" Pressure = "0" />
		<Point X = "-4.835402" Y = "-3.672062" T = "0" Pressure = "0" />
		<Point X = "-4.726072" Y = "-3.722363" T = "0" Pressure = "0" />
		<Point X = "-4.630069" Y = "-3.759149" T = "0" Pressure = "0" />
		<Point X = "-4.48368" Y = "-3.805261" T = "0" Pressure = "0" />
		<Point X = "-4.35945" Y = "-3.838063" T = "0" Pressure = "0" />
		<Point X = "-4.205528" Y = "-3.871825" T = "0" Pressure = "0" />
		<Point X = "-4.092173" Y = "-3.891166" T = "0" Pressure = "0" />
		<Point X = "-3.993856" Y = "-3.903804" T = "0" Pressure = "0" />
		<Point X = "-3.866619" Y = "-3.911962" T = "0" Pressure = "0" />
		<Point X = "-3.764475" Y = "-3.91113" T = "0" Pressure = "0" />
		<Point X = "-3.680053" Y = "-3.906175" T = "0" Pressure = "0" />
		<Point X = "-3.615892" Y = "-3.900069" T = "0" Pressure = "0" />
		<Point X = "-3.532483" Y = "-3.890352" T = "0" Pressure = "0" />
		<Point X = "-3.452151" Y = "-3.88068" T = "0" Pressure = "0" />
		<Point X = "-3.392265" Y = "-3.872407" T = "0" Pressure = "0" />
		<Point X = "-3.313484" Y = "-3.858385" T = "0" Pressure = "0" />
		<Point X = "-3.23192" Y = "-3.841069" T = "0" Pressure = "0" />
		<Point X = "-3.173085" Y = "-3.827504" T = "0" Pressure = "0" />
		<Point X = "-3.092043" Y = "-3.807765" T = "0" Pressure = "0" />
		<Point X = "-3.050561" Y = "-3.797283" T = "0" Pressure = "0" />
		<Point X = "-2.990443" Y = "-3.772006" T = "0" Pressure = "0" />
		<Point X = "-2.971725" Y = "-3.758377" T = "0" Pressure = "0" />
		<Point X = "-2.954128" Y = "-3.733793" T = "0" Pressure = "0" />
		<Point X = "-2.945122" Y = "-3.694629" T = "0" Pressure = "0" />
		<Point X = "-2.945866" Y = "-3.657172" T = "0" Pressure = "0" />
		<Point X = "-2.95614" Y = "-3.600522" T = "0" Pressure = "0" />
		<Point X = "-2.968575" Y = "-3.553018" T = "0" Pressure = "0" />
		<Point X = "-2.983571" Y = "-3.501838" T = "0" Pressure = "0" />
		<Point X = "-2.994748" Y = "-3.468608" T = "0" Pressure = "0" />
		<Point X = "-3.016855" Y = "-3.41277" T = "0" Pressure = "0" />
		<Point X = "-3.042019" Y = "-3.355031" T = "0" Pressure = "0" />
		<Point X = "-3.061001" Y = "-3.314409" T = "0" Pressure = "0" />
		<Point X = "-3.089853" Y = "-3.256834" T = "0" Pressure = "0" />
		<Point X = "-3.1159" Y = "-3.207511" T = "0" Pressure = "0" />
		<Point X = "-3.141129" Y = "-3.158814" T = "0" Pressure = "0" />
		<Point X = "-3.171734" Y = "-3.099863" T = "0" Pressure = "0" />
		<Point X = "-3.188169" Y = "-3.06953" T = "0" Pressure = "0" />
		<Point X = "-3.214046" Y = "-3.024612" T = "0" Pressure = "0" />
		<Point X = "-3.237313" Y = "-2.988078" T = "0" Pressure = "0" />
		<Point X = "-3.259446" Y = "-2.95552" T = "0" Pressure = "0" />
		<Point X = "-3.300638" Y = "-2.894798" T = "0" Pressure = "0" />
		<Point X = "-3.329358" Y = "-2.851589" T = "0" Pressure = "0" />
		<Point X = "-3.349187" Y = "-2.821459" T = "0" Pressure = "0" />
		<Point X = "-3.375324" Y = "-2.781436" T = "0" Pressure = "0" />
		<Point X = "-3.396954" Y = "-2.748091" T = "0" Pressure = "0" />
		<Point X = "-3.425772" Y = "-2.704625" T = "0" Pressure = "0" />
		<Point X = "-3.449741" Y = "-2.669484" T = "0" Pressure = "0" />
		<Point X = "-3.470165" Y = "-2.639905" T = "0" Pressure = "0" />
		<Point X = "-3.506665" Y = "-2.587319" T = "0" Pressure = "0" />
		<Point X = "-3.548809" Y = "-2.52941" T = "0" Pressure = "0" />
		<Point X = "-3.587074" Y = "-2.478151" T = "0" Pressure = "0" />
		<Point X = "-3.61375" Y = "-2.442474" T = "0" Pressure = "0" />
		<Point X = "-3.657551" Y = "-2.387967" T = "0" Pressure = "0" />
		<Point X = "-3.700759" Y = "-2.338248" T = "0" Pressure = "0" />
		<Point X = "-3.759238" Y = "-2.272188" T = "0" Pressure = "0" />
		<Point X = "-3.802567" Y = "-2.222905" T = "0" Pressure = "0" />
		<Point X = "-3.828575" Y = "-2.193021" T = "0" Pressure = "0" />
		<Point X = "-3.88377" Y = "-2.128321" T = "0" Pressure = "0" />
		<Point X = "-3.930335" Y = "-2.072961" T = "0" Pressure = "0" />
		<Point X = "-3.992525" Y = "-2.000045" T = "0" Pressure = "0" />
		<Point X = "-4.045966" Y = "-1.937291" T = "0" Pressure = "0" />
		<Point X = "-4.082785" Y = "-1.893261" T = "0" Pressure = "0" />
		<Point X = "-4.137321" Y = "-1.827301" T = "0" Pressure = "0" />
		<Point X = "-4.200737" Y = "-1.751818" T = "0" Pressure = "0" />
		<Point X = "-4.258254" Y = "-1.684945" T = "0" Pressure = "0" />
		<Point X = "-4.329307" Y = "-1.603424" T = "0" Pressure = "0" />
		<Point X = "-4.354458" Y = "-1.57477" T = "0" Pressure = "0" />
		<Point X = "-4.392123" Y = "-1.532014" T = "0" Pressure = "0" />
		<Point X = "-4.445296" Y = "-1.471926" T = "0" Pressure = "0" />
		<Point X = "-4.480782" Y = "-1.431176" T = "0" Pressure = "0" />
		<Point X = "-4.514985" Y = "-1.390497" T = "0" Pressure = "0" />
		<Point X = "-4.565722" Y = "-1.327307" T = "0" Pressure = "0" />
		<Point X = "-4.598457" Y = "-1.28547" T = "0" Pressure = "0" />
		<Point X = "-4.6649" Y = "-1.198063" T = "0" Pressure = "0" />
		<Point X = "-4.718249" Y = "-1.126052" T = "0" Pressure = "0" />
		<Point X = "-4.761955" Y = "-1.066437" T = "0" Pressure = "0" />
		<Point X = "-4.835262" Y = "-0.9640058" T = "0" Pressure = "0" />
		<Point X = "-4.883375" Y = "-0.8944995" T = "0" Pressure = "0" />
		<Point X = "-4.939574" Y = "-0.811147" T = "0" Pressure = "0" />
		<Point X = "-4.995673" Y = "-0.7272496" T = "0" Pressure = "0" />
		<Point X = "-5.046961" Y = "-0.6490309" T = "0" Pressure = "0" />
		<Point X = "-5.113554" Y = "-0.5434638" T = "0" Pressure = "0" />
		<Point X = "-5.154865" Y = "-0.4760344" T = "0" Pressure = "0" />
		<Point X = "-5.190447" Y = "-0.4156702" T = "0" Pressure = "0" />
		<Point X = "-5.226879" Y = "-0.3502893" T = "0" Pressure = "0" />
		<Point X = "-5.259151" Y = "-0.289544" T = "0" Pressure = "0" />
		<Point X = "-5.279767" Y = "-0.2486784" T = "0" Pressure = "0" />
		<Point X = "-5.304989" Y = "-0.1929796" T = "0" Pressure = "0" />
		<Point X = "-5.327678" Y = "-0.1363309" T = "0" Pressure = "0" />
		<Point X = "-5.348436" Y = "-0.07999759" T = "0" Pressure = "0" />
		<Point X = "-5.368821" Y = "-0.02100415" T = "0" Pressure = "0" />
		<Point X = "-5.383025" Y = "0.02208243" T = "0" Pressure = "0" />
		<Point X = "-5.391123" Y = "0.0473459" T = "0" Pressure = "0" />
		<Point X = "-5.404309" Y = "0.09995779" T = "0" Pressure = "0" />
		<Point X = "-5.409403" Y = "0.1280268" T = "0" Pressure = "0" />
		<Point X = "-5.412955" Y = "0.1655409" T = "0" Pressure = "0" />
		<Point X = "-5.413095" Y = "0.2325664" T = "0" Pressure = "0" />
		<Point X = "-5.411944" Y = "0.2594922" T = "0" Pressure = "0" />
		<Point X = "-5.406453" Y = "0.3303401" T = "0" Pressure = "0" />
		<Point X = "-5.399612" Y = "0.3913684" T = "0" Pressure = "0" />
		<Point X = "-5.394565" Y = "0.4288839" T = "0" Pressure = "0" />
		<Point X = "-5.38622" Y = "0.4855084" T = "0" Pressure = "0" />
		<Point X = "-5.379752" Y = "0.5274256" T = "0" Pressure = "0" />
		<Point X = "-5.373432" Y = "0.5676121" T = "0" Pressure = "0" />
		<Point X = "-5.360641" Y = "0.6467472" T = "0" Pressure = "0" />
		<Point X = "-5.350751" Y = "0.7035502" T = "0" Pressure = "0" />
		<Point X = "-5.338599" Y = "0.7698135" T = "0" Pressure = "0" />
		<Point X = "-5.319971" Y = "0.8690487" T = "0" Pressure = "0" />
		<Point X = "-5.306755" Y = "0.9457813" T = "0" Pressure = "0" />
		<Point X = "-5.292375" Y = "1.045193" T = "0" Pressure = "0" />
		<Point X = "-5.28896" Y = "1.069132" T = "0" Pressure = "0" />
		<Point X = "-5.279497" Y = "1.125908" T = "0" Pressure = "0" />
		<Point X = "-5.269317" Y = "1.18006" T = "0" Pressure = "0" />
		<Point X = "-5.262887" Y = "1.21228" T = "0" Pressure = "0" />
		<Point X = "-5.254261" Y = "1.253855" T = "0" Pressure = "0" />
		<Point X = "-5.249192" Y = "1.277594" T = "0" Pressure = "0" />
		<Point X = "-5.239664" Y = "1.315105" T = "0" Pressure = "0" />
		<Point X = "-5.228746" Y = "1.351644" T = "0" Pressure = "0" />
		<Point X = "-5.216305" Y = "1.384952" T = "0" Pressure = "0" />
		<Point X = "-5.179629" Y = "1.456482" T = "0" Pressure = "0" />
		<Point X = "-5.153624" Y = "1.500796" T = "0" Pressure = "0" />
		<Point X = "-5.111626" Y = "1.566462" T = "0" Pressure = "0" />
		<Point X = "-5.084228" Y = "1.606598" T = "0" Pressure = "0" />
		<Point X = "-5.058037" Y = "1.642141" T = "0" Pressure = "0" />
		<Point X = "-5.005943" Y = "1.703626" T = "0" Pressure = "0" />
		<Point X = "-4.969281" Y = "1.741827" T = "0" Pressure = "0" />
		<Point X = "-4.920069" Y = "1.784569" T = "0" Pressure = "0" />
		<Point X = "-4.890144" Y = "1.80709" T = "0" Pressure = "0" />
		<Point X = "-4.824004" Y = "1.846675" T = "0" Pressure = "0" />
		<Point X = "-4.790617" Y = "1.863023" T = "0" Pressure = "0" />
		<Point X = "-4.739765" Y = "1.884774" T = "0" Pressure = "0" />
		<Point X = "-4.672885" Y = "1.906219" T = "0" Pressure = "0" />
		<Point X = "-4.616423" Y = "1.918231" T = "0" Pressure = "0" />
		<Point X = "-4.537399" Y = "1.927657" T = "0" Pressure = "0" />
		<Point X = "-4.507412" Y = "1.929445" T = "0" Pressure = "0" />
		<Point X = "-4.446639" Y = "1.930149" T = "0" Pressure = "0" />
		<Point X = "-4.391282" Y = "1.928369" T = "0" Pressure = "0" />
		<Point X = "-4.348304" Y = "1.925793" T = "0" Pressure = "0" />
		<Point X = "-4.298441" Y = "1.916531" T = "0" Pressure = "0" />
		<Point X = "-4.257937" Y = "1.903484" T = "0" Pressure = "0" />
		<Point X = "-4.202005" Y = "1.882572" T = "0" Pressure = "0" />
		<Point X = "-4.142123" Y = "1.862667" T = "0" Pressure = "0" />
		<Point X = "-4.056015" Y = "1.838714" T = "0" Pressure = "0" />
		<Point X = "-4.013515" Y = "1.827905" T = "0" Pressure = "0" />
		<Point X = "-3.951387" Y = "1.812915" T = "0" Pressure = "0" />
		<Point X = "-3.873855" Y = "1.794856" T = "0" Pressure = "0" />
		<Point X = "-3.822451" Y = "1.782874" T = "0" Pressure = "0" />
		<Point X = "-3.766901" Y = "1.769412" T = "0" Pressure = "0" />
		<Point X = "-3.693392" Y = "1.748532" T = "0" Pressure = "0" />
		<Point X = "-3.647246" Y = "1.733359" T = "0" Pressure = "0" />
		<Point X = "-3.591712" Y = "1.712106" T = "0" Pressure = "0" />
		<Point X = "-3.52423" Y = "1.677444" T = "0" Pressure = "0" />
		<Point X = "-3.455088" Y = "1.630969" T = "0" Pressure = "0" />
		<Point X = "-3.409881" Y = "1.594114" T = "0" Pressure = "0" />
		<Point X = "-3.33302" Y = "1.51998" T = "0" Pressure = "0" />
		<Point X = "-3.282879" Y = "1.468371" T = "0" Pressure = "0" />
		<Point X = "-3.219033" Y = "1.400579" T = "0" Pressure = "0" />
		<Point X = "-3.184606" Y = "1.361872" T = "0" Pressure = "0" />
		<Point X = "-3.156172" Y = "1.328131" T = "0" Pressure = "0" />
		<Point X = "-3.116721" Y = "1.279174" T = "0" Pressure = "0" />
		<Point X = "-3.091698" Y = "1.247025" T = "0" Pressure = "0" />
		<Point X = "-3.061688" Y = "1.207563" T = "0" Pressure = "0" />
		<Point X = "-3.023179" Y = "1.151083" T = "0" Pressure = "0" />
		<Point X = "-2.991815" Y = "1.10093" T = "0" Pressure = "0" />
		<Point X = "-2.952267" Y = "1.031866" T = "0" Pressure = "0" />
		<Point X = "-2.917273" Y = "0.9654092" T = "0" Pressure = "0" />
		<Point X = "-2.881344" Y = "0.8925459" T = "0" Pressure = "0" />
		<Point X = "-2.852119" Y = "0.8297225" T = "0" Pressure = "0" />
		<Point X = "-2.818576" Y = "0.7515568" T = "0" Pressure = "0" />
		<Point X = "-2.784849" Y = "0.6659694" T = "0" Pressure = "0" />
		<Point X = "-2.755851" Y = "0.5849804" T = "0" Pressure = "0" />
		<Point X = "-2.728435" Y = "0.4982266" T = "0" Pressure = "0" />
		<Point X = "-2.710569" Y = "0.4357414" T = "0" Pressure = "0" />
		<Point X = "-2.689923" Y = "0.3535754" T = "0" Pressure = "0" />
		<Point X = "-2.676947" Y = "0.2917108" T = "0" Pressure = "0" />
		<Point X = "-2.668961" Y = "0.2453719" T = "0" Pressure = "0" />
		<Point X = "-2.657446" Y = "0.1384968" T = "0" Pressure = "0" />
		<Point X = "-2.654119" Y = "0.07339647" T = "0" Pressure = "0" />
		<Point X = "-2.654149" Y = "-0.0008201599" T = "0" Pressure = "0" />
		<Point X = "-2.659117" Y = "-0.0700086" T = "0" Pressure = "0" />
		<Point X = "-2.665379" Y = "-0.1170676" T = "0" Pressure = "0" />
		<Point X = "-2.684585" Y = "-0.2122188" T = "0" Pressure = "0" />
		<Point X = "-2.699837" Y = "-0.2715819" T = "0" Pressure = "0" />
		<Point X = "-2.714649" Y = "-0.3234893" T = "0" Pressure = "0" />
		<Point X = "-2.740067" Y = "-0.3987617" T = "0" Pressure = "0" />
		<Point X = "-2.765673" Y = "-0.4579146" T = "0" Pressure = "0" />
		<Point X = "-2.797422" Y = "-0.5183347" T = "0" Pressure = "0" />
		<Point X = "-2.822879" Y = "-0.5617065" T = "0" Pressure = "0" />
		<Point X = "-2.858911" Y = "-0.6181365" T = "0" Pressure = "0" />
		<Point X = "-2.893281" Y = "-0.6669634" T = "0" Pressure = "0" />
		<Point X = "-2.923631" Y = "-0.7056351" T = "0" Pressure = "0" />
		<Point X = "-2.964046" Y = "-0.7517497" T = "0" Pressure = "0" />
		<Point X = "-2.999879" Y = "-0.7883835" T = "0" Pressure = "0" />
		<Point X = "-3.060259" Y = "-0.838451" T = "0" Pressure = "0" />
		<Point X = "-3.12404" Y = "-0.8805" T = "0" Pressure = "0" />
		<Point X = "-3.169343" Y = "-0.9065145" T = "0" Pressure = "0" />
		<Point X = "-3.253525" Y = "-0.9501902" T = "0" Pressure = "0" />
		<Point X = "-3.323393" Y = "-0.9863146" T = "0" Pressure = "0" />
		<Point X = "-3.373007" Y = "-1.014011" T = "0" Pressure = "0" />
		<Point X = "-3.438302" Y = "-1.058538" T = "0" Pressure = "0" />
		<Point X = "-3.472054" Y = "-1.08593" T = "0" Pressure = "0" />
		<Point X = "-3.52773" Y = "-1.141195" T = "0" Pressure = "0" />
		<Point X = "-3.554623" Y = "-1.172749" T = "0" Pressure = "0" />
		<Point X = "-3.591061" Y = "-1.216674" T = "0" Pressure = "0" />
		<Point X = "-3.62369" Y = "-1.255737" T = "0" Pressure = "0" />
		<Point X = "-3.638726" Y = "-1.273708" T = "0" Pressure = "0" />
		<Point X = "-3.683696" Y = "-1.327371" T = "0" Pressure = "0" />
		<Point X = "-3.713696" Y = "-1.363115" T = "0" Pressure = "0" />
		<Point X = "-3.727447" Y = "-1.379139" T = "0" Pressure = "0" />
		<Point X = "-3.748022" Y = "-1.397896" T = "0" Pressure = "0" />
		<Point X = "-3.792708" Y = "-1.424046" T = "0" Pressure = "0" />
		<Point X = "-3.83277" Y = "-1.442337" T = "0" Pressure = "0" />
		<Point X = "-3.871265" Y = "-1.457311" T = "0" Pressure = "0" />
	</Stroke>
</Gesture>
