<?xml version="1.0" encoding="utf-8" standalone="yes"?>
<Gesture Name = "e inval">
	<Stroke>
		<Point X = "-6.894083" Y = "3.407043" T = "0" Pressure = "0" />
		<Point X = "-6.750913" Y = "3.482835" T = "0" Pressure = "0" />
		<Point X = "-6.565589" Y = "3.56911" T = "0" Pressure = "0" />
		<Point X = "-6.471453" Y = "3.605629" T = "0" Pressure = "0" />
		<Point X = "-6.352557" Y = "3.644813" T = "0" Pressure = "0" />
		<Point X = "-6.182628" Y = "3.68456" T = "0" Pressure = "0" />
		<Point X = "-6.070853" Y = "3.702399" T = "0" Pressure = "0" />
		<Point X = "-5.953651" Y = "3.715308" T = "0" Pressure = "0" />
		<Point X = "-5.756079" Y = "3.718709" T = "0" Pressure = "0" />
		<Point X = "-5.643697" Y = "3.711093" T = "0" Pressure = "0" />
		<Point X = "-5.514597" Y = "3.695142" T = "0" Pressure = "0" />
		<Point X = "-5.335144" Y = "3.655463" T = "0" Pressure = "0" />
		<Point X = "-5.270318" Y = "3.571423" T = "0" Pressure = "0" />
		<Point X = "-5.297644" Y = "3.423753" T = "0" Pressure = "0" />
		<Point X = "-5.425866" Y = "3.087951" T = "0" Pressure = "0" />
		<Point X = "-5.512319" Y = "2.862442" T = "0" Pressure = "0" />
		<Point X = "-5.599134" Y = "2.612407" T = "0" Pressure = "0" />
		<Point X = "-5.698561" Y = "2.305051" T = "0" Pressure = "0" />
		<Point X = "-5.751228" Y = "2.134428" T = "0" Pressure = "0" />
		<Point X = "-5.796243" Y = "1.98469" T = "0" Pressure = "0" />
		<Point X = "-5.84319" Y = "1.791151" T = "0" Pressure = "0" />
		<Point X = "-5.770202" Y = "1.59185" T = "0" Pressure = "0" />
		<Point X = "-5.606101" Y = "1.342263" T = "0" Pressure = "0" />
		<Point X = "-5.229855" Y = "0.893567" T = "0" Pressure = "0" />
		<Point X = "-4.90728" Y = "0.5513806" T = "0" Pressure = "0" />
		<Point X = "-4.579579" Y = "0.2276132" T = "0" Pressure = "0" />
		<Point X = "-4.128764" Y = "-0.1829533" T = "0" Pressure = "0" />
		<Point X = "-3.784042" Y = "-0.4756944" T = "0" Pressure = "0" />
		<Point X = "-3.48308" Y = "-0.7176005" T = "0" Pressure = "0" />
		<Point X = "-3.12773" Y = "-0.9874755" T = "0" Pressure = "0" />
		<Point X = "-2.848775" Y = "-1.189741" T = "0" Pressure = "0" />
		<Point X = "-2.603786" Y = "-1.363195" T = "0" Pressure = "0" />
		<Point X = "-2.32397" Y = "-1.561055" T = "0" Pressure = "0" />
		<Point X = "-2.10302" Y = "-1.71997" T = "0" Pressure = "0" />
		<Point X = "-1.917013" Y = "-1.855519" T = "0" Pressure = "0" />
		<Point X = "-1.689323" Y = "-2.01848" T = "0" Pressure = "0" />
		<Point X = "-1.485001" Y = "-2.160802" T = "0" Pressure = "0" />
		<Point X = "-1.327811" Y = "-2.269408" T = "0" Pressure = "0" />
		<Point X = "-1.174149" Y = "-2.376626" T = "0" Pressure = "0" />
		<Point X = "-1.00336" Y = "-2.497295" T = "0" Pressure = "0" />
		<Point X = "-0.9065026" Y = "-2.568546" T = "0" Pressure = "0" />
		<Point X = "-0.8187485" Y = "-2.638084" T = "0" Pressure = "0" />
		<Point X = "-0.7203369" Y = "-2.727611" T = "0" Pressure = "0" />
		<Point X = "-0.6806946" Y = "-2.770583" T = "0" Pressure = "0" />
		<Point X = "-0.6432207" Y = "-2.820513" T = "0" Pressure = "0" />
		<Point X = "-0.6233665" Y = "-2.865639" T = "0" Pressure = "0" />
		<Point X = "-0.621905" Y = "-2.889144" T = "0" Pressure = "0" />
		<Point X = "-0.6280306" Y = "-2.909459" T = "0" Pressure = "0" />
		<Point X = "-0.6280306" Y = "-2.909459" T = "0" Pressure = "0" />
		<Point X = "-0.6394026" Y = "-2.921969" T = "0" Pressure = "0" />
		<Point X = "-0.6700686" Y = "-2.910982" T = "0" Pressure = "0" />
		<Point X = "-0.7537833" Y = "-2.83539" T = "0" Pressure = "0" />
		<Point X = "-0.8177388" Y = "-2.768202" T = "0" Pressure = "0" />
		<Point X = "-0.916743" Y = "-2.658875" T = "0" Pressure = "0" />
		<Point X = "-1.157322" Y = "-2.369081" T = "0" Pressure = "0" />
		<Point X = "-1.329442" Y = "-2.154477" T = "0" Pressure = "0" />
		<Point X = "-1.539717" Y = "-1.881901" T = "0" Pressure = "0" />
		<Point X = "-1.813975" Y = "-1.473752" T = "0" Pressure = "0" />
		<Point X = "-1.983023" Y = "-1.18765" T = "0" Pressure = "0" />
		<Point X = "-2.152014" Y = "-0.8686795" T = "0" Pressure = "0" />
		<Point X = "-2.347553" Y = "-0.4600169" T = "0" Pressure = "0" />
		<Point X = "-2.467754" Y = "-0.1810044" T = "0" Pressure = "0" />
		<Point X = "-2.571248" Y = "0.09395938" T = "0" Pressure = "0" />
		<Point X = "-2.693807" Y = "0.4827304" T = "0" Pressure = "0" />
		<Point X = "-2.743844" Y = "0.6699765" T = "0" Pressure = "0" />
		<Point X = "-2.797597" Y = "0.9170935" T = "0" Pressure = "0" />
		<Point X = "-2.849772" Y = "1.219551" T = "0" Pressure = "0" />
		<Point X = "-2.878394" Y = "1.430754" T = "0" Pressure = "0" />
		<Point X = "-2.89333" Y = "1.608842" T = "0" Pressure = "0" />
		<Point X = "-2.896984" Y = "1.808374" T = "0" Pressure = "0" />
		<Point X = "-2.889912" Y = "1.981549" T = "0" Pressure = "0" />
		<Point X = "-2.882986" Y = "2.081647" T = "0" Pressure = "0" />
		<Point X = "-2.875643" Y = "2.200864" T = "0" Pressure = "0" />
		<Point X = "-2.871888" Y = "2.281809" T = "0" Pressure = "0" />
		<Point X = "-2.869425" Y = "2.337997" T = "0" Pressure = "0" />
		<Point X = "-2.869425" Y = "2.337997" T = "0" Pressure = "0" />
		<Point X = "-2.869425" Y = "2.337997" T = "0" Pressure = "0" />
		<Point X = "-2.869425" Y = "2.337997" T = "0" Pressure = "0" />
		<Point X = "-2.869425" Y = "2.337997" T = "0" Pressure = "0" />
		<Point X = "-2.869425" Y = "2.337997" T = "0" Pressure = "0" />
		<Point X = "-2.869425" Y = "2.337997" T = "0" Pressure = "0" />
		<Point X = "-2.854826" Y = "2.375199" T = "0" Pressure = "0" />
		<Point X = "-2.8137" Y = "2.377608" T = "0" Pressure = "0" />
		<Point X = "-2.772158" Y = "2.362147" T = "0" Pressure = "0" />
		<Point X = "-2.717281" Y = "2.33432" T = "0" Pressure = "0" />
		<Point X = "-2.629772" Y = "2.281028" T = "0" Pressure = "0" />
		<Point X = "-2.568797" Y = "2.238399" T = "0" Pressure = "0" />
		<Point X = "-2.498851" Y = "2.183024" T = "0" Pressure = "0" />
		<Point X = "-2.419621" Y = "2.110552" T = "0" Pressure = "0" />
		<Point X = "-2.370611" Y = "2.057371" T = "0" Pressure = "0" />
		<Point X = "-2.395472" Y = "1.872072" T = "0" Pressure = "0" />
		<Point X = "-2.485561" Y = "1.557992" T = "0" Pressure = "0" />
		<Point X = "-2.521641" Y = "1.433531" T = "0" Pressure = "0" />
		<Point X = "-2.543094" Y = "1.352075" T = "0" Pressure = "0" />
		<Point X = "-2.538943" Y = "1.329543" T = "0" Pressure = "0" />
		<Point X = "-2.522683" Y = "1.353266" T = "0" Pressure = "0" />
		<Point X = "-2.488776" Y = "1.420404" T = "0" Pressure = "0" />
		<Point X = "-2.419406" Y = "1.579271" T = "0" Pressure = "0" />
		<Point X = "-2.363371" Y = "1.726185" T = "0" Pressure = "0" />
		<Point X = "-2.315838" Y = "1.883313" T = "0" Pressure = "0" />
		<Point X = "-2.267627" Y = "2.113557" T = "0" Pressure = "0" />
		<Point X = "-2.245136" Y = "2.294933" T = "0" Pressure = "0" />
		<Point X = "-2.232189" Y = "2.488899" T = "0" Pressure = "0" />
		<Point X = "-2.220161" Y = "2.75454" T = "0" Pressure = "0" />
		<Point X = "-2.204154" Y = "2.939129" T = "0" Pressure = "0" />
		<Point X = "-2.168599" Y = "3.159707" T = "0" Pressure = "0" />
		<Point X = "-2.114357" Y = "3.411289" T = "0" Pressure = "0" />
		<Point X = "-2.087957" Y = "3.517742" T = "0" Pressure = "0" />
		<Point X = "-2.054179" Y = "3.633018" T = "0" Pressure = "0" />
		<Point X = "-2.072478" Y = "3.757408" T = "0" Pressure = "0" />
		<Point X = "-2.133341" Y = "3.80104" T = "0" Pressure = "0" />
		<Point X = "-2.230754" Y = "3.832148" T = "0" Pressure = "0" />
		<Point X = "-2.399851" Y = "3.84008" T = "0" Pressure = "0" />
		<Point X = "-2.511633" Y = "3.827275" T = "0" Pressure = "0" />
		<Point X = "-2.641389" Y = "3.798267" T = "0" Pressure = "0" />
		<Point X = "-2.810494" Y = "3.739728" T = "0" Pressure = "0" />
		<Point X = "-2.926848" Y = "3.690944" T = "0" Pressure = "0" />
		<Point X = "-3.002308" Y = "3.64759" T = "0" Pressure = "0" />
		<Point X = "-2.990356" Y = "3.614457" T = "0" Pressure = "0" />
		<Point X = "-2.927205" Y = "3.59344" T = "0" Pressure = "0" />
		<Point X = "-2.841372" Y = "3.574569" T = "0" Pressure = "0" />
		<Point X = "-2.703145" Y = "3.538147" T = "0" Pressure = "0" />
		<Point X = "-2.580901" Y = "3.49059" T = "0" Pressure = "0" />
		<Point X = "-2.450396" Y = "3.413164" T = "0" Pressure = "0" />
		<Point X = "-2.269539" Y = "3.275298" T = "0" Pressure = "0" />
		<Point X = "-2.063711" Y = "3.080647" T = "0" Pressure = "0" />
		<Point X = "-1.871429" Y = "2.868439" T = "0" Pressure = "0" />
		<Point X = "-1.62237" Y = "2.562192" T = "0" Pressure = "0" />
		<Point X = "-1.425729" Y = "2.300479" T = "0" Pressure = "0" />
		<Point X = "-1.253404" Y = "2.057563" T = "0" Pressure = "0" />
		<Point X = "-1.060974" Y = "1.776402" T = "0" Pressure = "0" />
		<Point X = "-0.8811646" Y = "1.521615" T = "0" Pressure = "0" />
		<Point X = "-0.7350761" Y = "1.325179" T = "0" Pressure = "0" />
		<Point X = "-0.5954242" Y = "1.142769" T = "0" Pressure = "0" />
		<Point X = "-0.4440604" Y = "0.9496977" T = "0" Pressure = "0" />
		<Point X = "-0.360661" Y = "0.8452483" T = "0" Pressure = "0" />
		<Point X = "-0.2696898" Y = "0.7329577" T = "0" Pressure = "0" />
		<Point X = "-0.1752506" Y = "0.6223738" T = "0" Pressure = "0" />
		<Point X = "-0.1138713" Y = "0.5572082" T = "0" Pressure = "0" />
		<Point X = "-0.04142253" Y = "0.490807" T = "0" Pressure = "0" />
		<Point X = "0.05797916" Y = "0.4269519" T = "0" Pressure = "0" />
		<Point X = "0.1191932" Y = "0.4012659" T = "0" Pressure = "0" />
		<Point X = "0.1849086" Y = "0.381627" T = "0" Pressure = "0" />
		<Point X = "0.2651198" Y = "0.3701299" T = "0" Pressure = "0" />
		<Point X = "0.3037126" Y = "0.3730579" T = "0" Pressure = "0" />
		<Point X = "0.3284082" Y = "0.3850619" T = "0" Pressure = "0" />
		<Point X = "0.3337792" Y = "0.4316381" T = "0" Pressure = "0" />
		<Point X = "0.3201379" Y = "0.4740202" T = "0" Pressure = "0" />
		<Point X = "0.29039" Y = "0.5371895" T = "0" Pressure = "0" />
		<Point X = "0.224044" Y = "0.6569587" T = "0" Pressure = "0" />
		<Point X = "0.1550217" Y = "0.7737215" T = "0" Pressure = "0" />
		<Point X = "0.07880148" Y = "0.8979009" T = "0" Pressure = "0" />
		<Point X = "-0.08362155" Y = "1.170904" T = "0" Pressure = "0" />
		<Point X = "-0.1835319" Y = "1.343931" T = "0" Pressure = "0" />
		<Point X = "-0.2944548" Y = "1.542494" T = "0" Pressure = "0" />
		<Point X = "-0.4609934" Y = "1.867199" T = "0" Pressure = "0" />
		<Point X = "-0.5491019" Y = "2.048541" T = "0" Pressure = "0" />
		<Point X = "-0.6491902" Y = "2.260482" T = "0" Pressure = "0" />
		<Point X = "-0.8015239" Y = "2.575268" T = "0" Pressure = "0" />
		<Point X = "-0.8768921" Y = "2.725336" T = "0" Pressure = "0" />
		<Point X = "-0.9636086" Y = "2.898898" T = "0" Pressure = "0" />
		<Point X = "-1.235532" Y = "3.081748" T = "0" Pressure = "0" />
		<Point X = "-1.499795" Y = "3.142985" T = "0" Pressure = "0" />
		<Point X = "-1.785477" Y = "3.177245" T = "0" Pressure = "0" />
		<Point X = "-2.16314" Y = "3.196514" T = "0" Pressure = "0" />
		<Point X = "-2.413806" Y = "3.198497" T = "0" Pressure = "0" />
		<Point X = "-2.663813" Y = "3.193988" T = "0" Pressure = "0" />
		<Point X = "-2.918842" Y = "3.190038" T = "0" Pressure = "0" />
		<Point X = "-3.113213" Y = "3.194753" T = "0" Pressure = "0" />
		<Point X = "-3.287175" Y = "3.206382" T = "0" Pressure = "0" />
		<Point X = "-3.485288" Y = "3.232064" T = "0" Pressure = "0" />
		<Point X = "-3.608683" Y = "3.256349" T = "0" Pressure = "0" />
		<Point X = "-3.728136" Y = "3.284374" T = "0" Pressure = "0" />
		<Point X = "-3.872821" Y = "3.320985" T = "0" Pressure = "0" />
		<Point X = "-3.959774" Y = "3.341026" T = "0" Pressure = "0" />
		<Point X = "-4.044193" Y = "3.356529" T = "0" Pressure = "0" />
		<Point X = "-4.146465" Y = "3.370178" T = "0" Pressure = "0" />
		<Point X = "-4.203012" Y = "3.372703" T = "0" Pressure = "0" />
		<Point X = "-4.2593" Y = "3.367824" T = "0" Pressure = "0" />
		<Point X = "-4.319675" Y = "3.349719" T = "0" Pressure = "0" />
		<Point X = "-4.345132" Y = "3.334944" T = "0" Pressure = "0" />
	</Stroke>
</Gesture>
