<?xml version="1.0" encoding="utf-8" standalone="yes"?>
<Gesture Name = "y">
	<Stroke>
		<Point X = "357.5" Y = "-189.875" T = "0" Pressure = "0" />
		<Point X = "357.5" Y = "-189.875" T = "0" Pressure = "0" />
		<Point X = "357.5" Y = "-189.875" T = "0" Pressure = "0" />
		<Point X = "357.5" Y = "-189.875" T = "0" Pressure = "0" />
		<Point X = "357.5" Y = "-189.875" T = "0" Pressure = "0" />
		<Point X = "357.5" Y = "-189.875" T = "0" Pressure = "0" />
		<Point X = "357.5" Y = "-189.875" T = "0" Pressure = "0" />
		<Point X = "357.5" Y = "-189.875" T = "0" Pressure = "0" />
		<Point X = "357.5" Y = "-189.875" T = "0" Pressure = "0" />
		<Point X = "357.5" Y = "-189.875" T = "0" Pressure = "0" />
		<Point X = "357.5" Y = "-189.875" T = "0" Pressure = "0" />
		<Point X = "357.5" Y = "-189.875" T = "0" Pressure = "0" />
		<Point X = "357.5" Y = "-189.875" T = "0" Pressure = "0" />
		<Point X = "357.5" Y = "-189.875" T = "0" Pressure = "0" />
		<Point X = "357.5" Y = "-189.875" T = "0" Pressure = "0" />
		<Point X = "357.5" Y = "-189.875" T = "0" Pressure = "0" />
		<Point X = "357.5" Y = "-189.875" T = "0" Pressure = "0" />
		<Point X = "357.5" Y = "-189.875" T = "0" Pressure = "0" />
		<Point X = "357.5" Y = "-189.875" T = "0" Pressure = "0" />
		<Point X = "357.5" Y = "-189.875" T = "0" Pressure = "0" />
		<Point X = "357.5" Y = "-189.875" T = "0" Pressure = "0" />
		<Point X = "357.5" Y = "-189.875" T = "0" Pressure = "0" />
		<Point X = "357.5" Y = "-189.875" T = "0" Pressure = "0" />
		<Point X = "357.5" Y = "-189.875" T = "0" Pressure = "0" />
		<Point X = "357.5" Y = "-189.875" T = "0" Pressure = "0" />
		<Point X = "357.5" Y = "-189.875" T = "0" Pressure = "0" />
		<Point X = "357.5" Y = "-189.875" T = "0" Pressure = "0" />
		<Point X = "357.5" Y = "-189.875" T = "0" Pressure = "0" />
		<Point X = "357.5" Y = "-189.875" T = "0" Pressure = "0" />
		<Point X = "357.5" Y = "-189.875" T = "0" Pressure = "0" />
		<Point X = "357.5" Y = "-189.875" T = "0" Pressure = "0" />
		<Point X = "357.5" Y = "-189.875" T = "0" Pressure = "0" />
		<Point X = "357.5" Y = "-189.875" T = "0" Pressure = "0" />
		<Point X = "357.5" Y = "-189.875" T = "0" Pressure = "0" />
		<Point X = "357.5" Y = "-189.875" T = "0" Pressure = "0" />
		<Point X = "357.5" Y = "-189.875" T = "0" Pressure = "0" />
		<Point X = "357.5" Y = "-189.875" T = "0" Pressure = "0" />
		<Point X = "357.5" Y = "-189.875" T = "0" Pressure = "0" />
		<Point X = "357.5" Y = "-189.875" T = "0" Pressure = "0" />
		<Point X = "357.5" Y = "-189.875" T = "0" Pressure = "0" />
		<Point X = "360" Y = "-187.375" T = "0" Pressure = "0" />
		<Point X = "368.75" Y = "-183.625" T = "0" Pressure = "0" />
		<Point X = "377.5" Y = "-179.875" T = "0" Pressure = "0" />
		<Point X = "377.5" Y = "-179.875" T = "0" Pressure = "0" />
		<Point X = "382.5" Y = "-176.125" T = "0" Pressure = "0" />
		<Point X = "392.5" Y = "-173.625" T = "0" Pressure = "0" />
		<Point X = "397.5" Y = "-171.125" T = "0" Pressure = "0" />
		<Point X = "401.25" Y = "-169.875" T = "0" Pressure = "0" />
		<Point X = "401.25" Y = "-169.875" T = "0" Pressure = "0" />
		<Point X = "407.5" Y = "-167.375" T = "0" Pressure = "0" />
		<Point X = "410" Y = "-164.875" T = "0" Pressure = "0" />
		<Point X = "417.5" Y = "-164.875" T = "0" Pressure = "0" />
		<Point X = "418.75" Y = "-163.625" T = "0" Pressure = "0" />
		<Point X = "418.75" Y = "-163.625" T = "0" Pressure = "0" />
		<Point X = "422.5" Y = "-162.375" T = "0" Pressure = "0" />
		<Point X = "428.75" Y = "-161.125" T = "0" Pressure = "0" />
		<Point X = "432.5" Y = "-159.875" T = "0" Pressure = "0" />
		<Point X = "432.5" Y = "-159.875" T = "0" Pressure = "0" />
		<Point X = "437.5" Y = "-159.875" T = "0" Pressure = "0" />
		<Point X = "447.5" Y = "-157.375" T = "0" Pressure = "0" />
		<Point X = "447.5" Y = "-157.375" T = "0" Pressure = "0" />
		<Point X = "447.5" Y = "-157.375" T = "0" Pressure = "0" />
		<Point X = "452.5" Y = "-154.875" T = "0" Pressure = "0" />
		<Point X = "452.5" Y = "-154.875" T = "0" Pressure = "0" />
		<Point X = "457.5" Y = "-154.875" T = "0" Pressure = "0" />
		<Point X = "457.5" Y = "-154.875" T = "0" Pressure = "0" />
		<Point X = "457.5" Y = "-154.875" T = "0" Pressure = "0" />
		<Point X = "460" Y = "-153.625" T = "0" Pressure = "0" />
		<Point X = "462.5" Y = "-153.625" T = "0" Pressure = "0" />
		<Point X = "463.75" Y = "-152.375" T = "0" Pressure = "0" />
		<Point X = "463.75" Y = "-152.375" T = "0" Pressure = "0" />
		<Point X = "466.25" Y = "-152.375" T = "0" Pressure = "0" />
		<Point X = "466.25" Y = "-152.375" T = "0" Pressure = "0" />
		<Point X = "466.25" Y = "-152.375" T = "0" Pressure = "0" />
		<Point X = "466.25" Y = "-152.375" T = "0" Pressure = "0" />
		<Point X = "466.25" Y = "-152.375" T = "0" Pressure = "0" />
		<Point X = "466.25" Y = "-152.375" T = "0" Pressure = "0" />
		<Point X = "466.25" Y = "-152.375" T = "0" Pressure = "0" />
		<Point X = "466.25" Y = "-152.375" T = "0" Pressure = "0" />
		<Point X = "466.25" Y = "-152.375" T = "0" Pressure = "0" />
		<Point X = "466.25" Y = "-152.375" T = "0" Pressure = "0" />
		<Point X = "466.25" Y = "-152.375" T = "0" Pressure = "0" />
		<Point X = "466.25" Y = "-152.375" T = "0" Pressure = "0" />
		<Point X = "466.25" Y = "-152.375" T = "0" Pressure = "0" />
		<Point X = "466.25" Y = "-152.375" T = "0" Pressure = "0" />
		<Point X = "466.25" Y = "-152.375" T = "0" Pressure = "0" />
		<Point X = "466.25" Y = "-152.375" T = "0" Pressure = "0" />
		<Point X = "466.25" Y = "-152.375" T = "0" Pressure = "0" />
		<Point X = "466.25" Y = "-152.375" T = "0" Pressure = "0" />
		<Point X = "466.25" Y = "-152.375" T = "0" Pressure = "0" />
		<Point X = "466.25" Y = "-152.375" T = "0" Pressure = "0" />
		<Point X = "466.25" Y = "-154.875" T = "0" Pressure = "0" />
		<Point X = "466.25" Y = "-159.875" T = "0" Pressure = "0" />
		<Point X = "466.25" Y = "-159.875" T = "0" Pressure = "0" />
		<Point X = "465" Y = "-167.375" T = "0" Pressure = "0" />
		<Point X = "461.25" Y = "-178.625" T = "0" Pressure = "0" />
		<Point X = "458.75" Y = "-191.125" T = "0" Pressure = "0" />
		<Point X = "458.75" Y = "-191.125" T = "0" Pressure = "0" />
		<Point X = "457.5" Y = "-199.875" T = "0" Pressure = "0" />
		<Point X = "457.5" Y = "-209.875" T = "0" Pressure = "0" />
		<Point X = "457.5" Y = "-214.875" T = "0" Pressure = "0" />
		<Point X = "457.5" Y = "-219.875" T = "0" Pressure = "0" />
		<Point X = "457.5" Y = "-219.875" T = "0" Pressure = "0" />
		<Point X = "457.5" Y = "-229.875" T = "0" Pressure = "0" />
		<Point X = "457.5" Y = "-243.625" T = "0" Pressure = "0" />
		<Point X = "457.5" Y = "-264.875" T = "0" Pressure = "0" />
		<Point X = "457.5" Y = "-264.875" T = "0" Pressure = "0" />
		<Point X = "460" Y = "-277.375" T = "0" Pressure = "0" />
		<Point X = "461.25" Y = "-286.125" T = "0" Pressure = "0" />
		<Point X = "462.5" Y = "-293.625" T = "0" Pressure = "0" />
		<Point X = "465" Y = "-299.875" T = "0" Pressure = "0" />
		<Point X = "465" Y = "-299.875" T = "0" Pressure = "0" />
		<Point X = "467.5" Y = "-319.875" T = "0" Pressure = "0" />
		<Point X = "470" Y = "-336.125" T = "0" Pressure = "0" />
		<Point X = "472.5" Y = "-352.375" T = "0" Pressure = "0" />
		<Point X = "472.5" Y = "-363.625" T = "0" Pressure = "0" />
		<Point X = "472.5" Y = "-363.625" T = "0" Pressure = "0" />
		<Point X = "473.75" Y = "-369.875" T = "0" Pressure = "0" />
		<Point X = "473.75" Y = "-378.625" T = "0" Pressure = "0" />
		<Point X = "477.5" Y = "-392.375" T = "0" Pressure = "0" />
		<Point X = "477.5" Y = "-392.375" T = "0" Pressure = "0" />
		<Point X = "477.5" Y = "-417.375" T = "0" Pressure = "0" />
		<Point X = "477.5" Y = "-417.375" T = "0" Pressure = "0" />
		<Point X = "477.5" Y = "-428.625" T = "0" Pressure = "0" />
		<Point X = "477.5" Y = "-437.375" T = "0" Pressure = "0" />
		<Point X = "477.5" Y = "-442.375" T = "0" Pressure = "0" />
		<Point X = "477.5" Y = "-442.375" T = "0" Pressure = "0" />
		<Point X = "477.5" Y = "-449.875" T = "0" Pressure = "0" />
		<Point X = "477.5" Y = "-449.875" T = "0" Pressure = "0" />
		<Point X = "477.5" Y = "-454.875" T = "0" Pressure = "0" />
		<Point X = "477.5" Y = "-459.875" T = "0" Pressure = "0" />
		<Point X = "477.5" Y = "-459.875" T = "0" Pressure = "0" />
		<Point X = "477.5" Y = "-466.125" T = "0" Pressure = "0" />
		<Point X = "477.5" Y = "-472.375" T = "0" Pressure = "0" />
		<Point X = "476.25" Y = "-479.875" T = "0" Pressure = "0" />
		<Point X = "476.25" Y = "-479.875" T = "0" Pressure = "0" />
		<Point X = "476.25" Y = "-486.125" T = "0" Pressure = "0" />
		<Point X = "476.25" Y = "-487.375" T = "0" Pressure = "0" />
		<Point X = "476.25" Y = "-491.125" T = "0" Pressure = "0" />
		<Point X = "476.25" Y = "-493.625" T = "0" Pressure = "0" />
		<Point X = "476.25" Y = "-494.875" T = "0" Pressure = "0" />
		<Point X = "476.25" Y = "-494.875" T = "0" Pressure = "0" />
		<Point X = "476.25" Y = "-497.375" T = "0" Pressure = "0" />
		<Point X = "476.25" Y = "-498.625" T = "0" Pressure = "0" />
		<Point X = "476.25" Y = "-499.875" T = "0" Pressure = "0" />
		<Point X = "476.25" Y = "-499.875" T = "0" Pressure = "0" />
		<Point X = "476.25" Y = "-499.875" T = "0" Pressure = "0" />
		<Point X = "476.25" Y = "-501.125" T = "0" Pressure = "0" />
		<Point X = "476.25" Y = "-501.125" T = "0" Pressure = "0" />
		<Point X = "476.25" Y = "-501.125" T = "0" Pressure = "0" />
		<Point X = "476.25" Y = "-502.375" T = "0" Pressure = "0" />
		<Point X = "476.25" Y = "-502.375" T = "0" Pressure = "0" />
		<Point X = "476.25" Y = "-502.375" T = "0" Pressure = "0" />
		<Point X = "476.25" Y = "-502.375" T = "0" Pressure = "0" />
		<Point X = "476.25" Y = "-502.375" T = "0" Pressure = "0" />
		<Point X = "476.25" Y = "-502.375" T = "0" Pressure = "0" />
		<Point X = "476.25" Y = "-502.375" T = "0" Pressure = "0" />
		<Point X = "476.25" Y = "-502.375" T = "0" Pressure = "0" />
		<Point X = "476.25" Y = "-502.375" T = "0" Pressure = "0" />
		<Point X = "476.25" Y = "-502.375" T = "0" Pressure = "0" />
		<Point X = "476.25" Y = "-503.625" T = "0" Pressure = "0" />
		<Point X = "476.25" Y = "-503.625" T = "0" Pressure = "0" />
		<Point X = "476.25" Y = "-504.875" T = "0" Pressure = "0" />
		<Point X = "476.25" Y = "-504.875" T = "0" Pressure = "0" />
		<Point X = "477.5" Y = "-504.875" T = "0" Pressure = "0" />
		<Point X = "477.5" Y = "-504.875" T = "0" Pressure = "0" />
		<Point X = "478.75" Y = "-506.125" T = "0" Pressure = "0" />
		<Point X = "481.25" Y = "-507.375" T = "0" Pressure = "0" />
		<Point X = "481.25" Y = "-507.375" T = "0" Pressure = "0" />
		<Point X = "485" Y = "-507.375" T = "0" Pressure = "0" />
		<Point X = "487.5" Y = "-507.375" T = "0" Pressure = "0" />
		<Point X = "492.5" Y = "-507.375" T = "0" Pressure = "0" />
		<Point X = "492.5" Y = "-507.375" T = "0" Pressure = "0" />
		<Point X = "498.75" Y = "-507.375" T = "0" Pressure = "0" />
		<Point X = "502.5" Y = "-504.875" T = "0" Pressure = "0" />
		<Point X = "512.5" Y = "-498.625" T = "0" Pressure = "0" />
		<Point X = "518.75" Y = "-494.875" T = "0" Pressure = "0" />
		<Point X = "518.75" Y = "-494.875" T = "0" Pressure = "0" />
		<Point X = "527.5" Y = "-488.625" T = "0" Pressure = "0" />
		<Point X = "537.5" Y = "-478.625" T = "0" Pressure = "0" />
		<Point X = "543.75" Y = "-471.125" T = "0" Pressure = "0" />
		<Point X = "543.75" Y = "-471.125" T = "0" Pressure = "0" />
		<Point X = "560" Y = "-458.625" T = "0" Pressure = "0" />
		<Point X = "560" Y = "-458.625" T = "0" Pressure = "0" />
		<Point X = "568.75" Y = "-451.125" T = "0" Pressure = "0" />
		<Point X = "576.25" Y = "-444.875" T = "0" Pressure = "0" />
		<Point X = "576.25" Y = "-444.875" T = "0" Pressure = "0" />
		<Point X = "581.25" Y = "-442.375" T = "0" Pressure = "0" />
		<Point X = "590" Y = "-436.125" T = "0" Pressure = "0" />
		<Point X = "593.75" Y = "-432.375" T = "0" Pressure = "0" />
		<Point X = "593.75" Y = "-432.375" T = "0" Pressure = "0" />
		<Point X = "605" Y = "-421.125" T = "0" Pressure = "0" />
		<Point X = "605" Y = "-421.125" T = "0" Pressure = "0" />
		<Point X = "608.75" Y = "-418.625" T = "0" Pressure = "0" />
		<Point X = "611.25" Y = "-414.875" T = "0" Pressure = "0" />
		<Point X = "611.25" Y = "-414.875" T = "0" Pressure = "0" />
		<Point X = "613.75" Y = "-411.125" T = "0" Pressure = "0" />
		<Point X = "616.25" Y = "-409.875" T = "0" Pressure = "0" />
		<Point X = "618.75" Y = "-407.375" T = "0" Pressure = "0" />
		<Point X = "618.75" Y = "-407.375" T = "0" Pressure = "0" />
		<Point X = "620" Y = "-406.125" T = "0" Pressure = "0" />
		<Point X = "622.5" Y = "-404.875" T = "0" Pressure = "0" />
		<Point X = "622.5" Y = "-404.875" T = "0" Pressure = "0" />
	</Stroke>
</Gesture>
